<?xml version="1.0" encoding="utf-8"?>
<bwFrame xmlns:xsi="http://www.w3.org/2001/XMLSchema-instance" xmlns:xsd="http://www.w3.org/2001/XMLSchema" default_layout="npnxnanbnsnfns00001100111" textdirection="ltr" textengine="DirectWrite" device="false" fontscale="100" captionFontScale="100" kbshortcuts="false" skip_nav_enabled="true" chromeless="false" outputtype="undefined" theme="unified" themeAccentColor="0x4FBDF4">
  <layouts>
    <layout name="npnxnanbsnfns00001100111" font="Lato" controllayout="npnxnanbsnfns00001100111" colorscheme="npnxnanbnsnfns00001100111" string_table="npnxnanbnsnfns00001100111" />
    <layout name="pxabnsnfns00001100111" font="Lato" controllayout="pxabnsnfns00001100111" colorscheme="npnxnanbnsnfns00001100111" string_table="npnxnanbnsnfns00001100111" />
    <layout name="npxnabnsnfns00001100111" font="Lato" controllayout="npxnabnsnfns00001100111" colorscheme="npnxnanbnsnfns00001100111" string_table="npnxnanbnsnfns00001100111" />
    <layout name="npnxnanbnsnfns00001100111" font="Lato" controllayout="npnxnanbnsnfns00001100111" colorscheme="npnxnanbnsnfns00001100111" string_table="npnxnanbnsnfns00001100111" />
    <layout name="pxabnsnfns00001100110" font="Lato" controllayout="pxabnsnfns00001100110" colorscheme="npnxnanbnsnfns00001100111" string_table="npnxnanbnsnfns00001100111" />
  </layouts>
  <control_options>
    <optiongroups>
      <optiongroup name="sidebaroptions">
        <options>
          <option name="title_enabled" value="true">
            <options>
              <option name="title_text" value="Sleep Disorders @ Storyline sample" />
            </options>
          </option>
          <option name="logo_enabled" value="false">
            <options />
          </option>
          <option name="sidebar_enabled" value="true">
            <options>
              <option name="sidebarpos" value="left" />
              <option name="closed" value="false" />
            </options>
          </option>
          <optionlist name="tabs">
            <listitems>
              <listitem name="resources" value="true" group="linkright" />
              <listitem name="outline" value="true" group="sidebar" />
              <listitem name="glossary" value="false" group="sidebar" />
              <listitem name="transcript" value="false" group="sidebar" />
            </listitems>
          </optionlist>
          <option name="time_enabled" value="false">
            <options>
              <option name="time_format" value="none" />
            </options>
          </option>
          <option name="video_enabled" value="false">
            <options>
              <option name="height" value="135" />
            </options>
          </option>
          <option name="logoAltText" />
        </options>
      </optiongroup>
      <optiongroup name="menuoptions">
        <options>
          <option name="flow" value="free" />
          <option name="wraplistitems" value="false" />
          <option name="tooltips" value="true" />
          <option name="autocollapse" value="true" />
          <option name="autonumber" value="false" />
          <option name="enableresultsicons" value="true" />
        </options>
      </optiongroup>
      <optiongroup name="controls">
        <options>
          <option name="volume" value="true" />
          <option name="seekbar" value="false">
            <options>
              <option name="readonly" value="false" />
              <option name="readonlyOnce" value="false" />
            </options>
          </option>
          <option name="pauseplay" value="false" />
          <option name="replay" value="false" />
          <option name="search" value="true" />
          <option name="closed_captions" value="true">
            <options>
              <option name="font" value="Lato" />
            </options>
          </option>
          <option name="settings" value="true" />
        </options>
      </optiongroup>
      <optiongroup name="bottombaroptions">
        <options>
          <option name="bottombar_enabled" value="true" />
        </options>
      </optiongroup>
      <optiongroup name="buttonoptions">
        <options>
          <option name="next" value="text" />
          <option name="previous" value="text" />
          <option name="submit" value="text" />
        </options>
      </optiongroup>
    </optiongroups>
  </control_options>
  <control_layouts>
    <control_layout name="npnxnanbsnfns00001100111">
      <control name="volume" enabled="true" />
      <control name="seekbar" enabled="false" />
      <control name="replay" enabled="false" />
      <control name="pauseplay" enabled="false" />
      <control name="logo" enabled="false" />
      <control name="previous" enabled="false" />
      <control name="next" enabled="false" />
      <control name="swipeleft" enabled="false" />
      <control name="swiperight" enabled="false" />
      <control name="submit" enabled="true" />
      <control name="finish" enabled="false" />
      <control name="submitall" enabled="false" />
      <control name="resources" enabled="true" />
      <control name="glossary" enabled="false" />
      <control name="transcript" enabled="false" />
      <control name="outline" enabled="true">
        <controls>
          <control name="search" enabled="true" />
        </controls>
      </control>
      <control name="close_btn" enabled="true" />
    </control_layout>
    <control_layout name="pxabnsnfns00001100111">
      <control name="volume" enabled="true" />
      <control name="seekbar" enabled="false" />
      <control name="replay" enabled="false" />
      <control name="pauseplay" enabled="false" />
      <control name="logo" enabled="false" />
      <control name="previous" enabled="true" />
      <control name="next" enabled="true" />
      <control name="swipeleft" enabled="true" />
      <control name="swiperight" enabled="true" />
      <control name="submit" enabled="false" />
      <control name="finish" enabled="false" />
      <control name="submitall" enabled="false" />
      <control name="resources" enabled="true" />
      <control name="glossary" enabled="false" />
      <control name="transcript" enabled="false" />
      <control name="outline" enabled="true">
        <controls>
          <control name="search" enabled="true" />
        </controls>
      </control>
      <control name="close_btn" enabled="true" />
    </control_layout>
    <control_layout name="npxnabnsnfns00001100111">
      <control name="volume" enabled="true" />
      <control name="seekbar" enabled="false" />
      <control name="replay" enabled="false" />
      <control name="pauseplay" enabled="false" />
      <control name="logo" enabled="false" />
      <control name="previous" enabled="false" />
      <control name="next" enabled="true" />
      <control name="swipeleft" enabled="false" />
      <control name="swiperight" enabled="true" />
      <control name="submit" enabled="false" />
      <control name="finish" enabled="false" />
      <control name="submitall" enabled="false" />
      <control name="resources" enabled="true" />
      <control name="glossary" enabled="false" />
      <control name="transcript" enabled="false" />
      <control name="outline" enabled="true">
        <controls>
          <control name="search" enabled="true" />
        </controls>
      </control>
      <control name="close_btn" enabled="true" />
    </control_layout>
    <control_layout name="npnxnanbnsnfns00001100111">
      <control name="volume" enabled="true" />
      <control name="seekbar" enabled="false" />
      <control name="replay" enabled="false" />
      <control name="pauseplay" enabled="false" />
      <control name="logo" enabled="false" />
      <control name="previous" enabled="false" />
      <control name="next" enabled="false" />
      <control name="swipeleft" enabled="false" />
      <control name="swiperight" enabled="false" />
      <control name="submit" enabled="false" />
      <control name="finish" enabled="false" />
      <control name="submitall" enabled="false" />
      <control name="resources" enabled="true" />
      <control name="glossary" enabled="false" />
      <control name="transcript" enabled="false" />
      <control name="outline" enabled="true">
        <controls>
          <control name="search" enabled="true" />
        </controls>
      </control>
      <control name="close_btn" enabled="true" />
    </control_layout>
    <control_layout name="pxabnsnfns00001100110">
      <control name="volume" enabled="true" />
      <control name="seekbar" enabled="false" />
      <control name="replay" enabled="false" />
      <control name="pauseplay" enabled="false" />
      <control name="logo" enabled="false" />
      <control name="previous" enabled="true" />
      <control name="next" enabled="true" />
      <control name="swipeleft" enabled="true" />
      <control name="swiperight" enabled="true" />
      <control name="submit" enabled="false" />
      <control name="finish" enabled="false" />
      <control name="submitall" enabled="false" />
      <control name="resources" enabled="true" />
      <control name="glossary" enabled="false" />
      <control name="transcript" enabled="false" />
      <control name="outline" enabled="true">
        <controls>
          <control name="search" enabled="true" />
        </controls>
      </control>
      <control name="close_btn" enabled="false" />
    </control_layout>
  </control_layouts>
  <colorschemes>
    <colorscheme name="npnxnanbnsnfns00001100111">
      <color_group name="accessibility">
        <group_colors>
          <color name="focus_rect">
            <fill type="linear" rotation="90">
              <colors>
                <color rgb="0xFFFF00" alpha="100" stop="0" />
              </colors>
            </fill>
          </color>
          <color name="focus_rect_secondary">
            <fill type="linear" rotation="90">
              <colors>
                <color rgb="0x002060" alpha="100" stop="0" />
              </colors>
            </fill>
          </color>
        </group_colors>
      </color_group>
      <color_group name="HTML">
        <group_colors>
          <color name="htmlpage_bg_color">
            <fill type="linear" rotation="90">
              <colors>
                <color rgb="0x282828" alpha="100" stop="0" />
              </colors>
            </fill>
          </color>
          <color name="preloader">
            <fill type="linear" rotation="90">
              <colors>
                <color rgb="0xFFFFFF" alpha="100" stop="0" />
              </colors>
            </fill>
          </color>
        </group_colors>
      </color_group>
      <color_group name="infopanel">
        <group_colors>
          <color name="link_text">
            <fill type="linear" rotation="90">
              <colors>
                <color rgb="0xBABBBA" alpha="100" stop="0" />
              </colors>
            </fill>
          </color>
          <color name="link_hover">
            <fill type="linear" rotation="90">
              <colors>
                <color rgb="0xFFFFFF" alpha="100" stop="0" />
              </colors>
            </fill>
          </color>
          <color name="shadow">
            <fill type="linear" rotation="90">
              <colors>
                <color rgb="0x000000" alpha="0" stop="0" />
              </colors>
            </fill>
          </color>
          <color name="bg">
            <fill type="linear" rotation="90">
              <colors>
                <color rgb="0xFFFFFF" alpha="100" stop="0" />
              </colors>
            </fill>
          </color>
          <color name="name_text">
            <fill type="linear" rotation="90">
              <colors>
                <color rgb="0x444444" alpha="100" stop="0" />
              </colors>
            </fill>
          </color>
          <color name="title_text">
            <fill type="linear" rotation="90">
              <colors>
                <color rgb="0x999999" alpha="100" stop="0" />
              </colors>
            </fill>
          </color>
        </group_colors>
      </color_group>
      <color_group name="infopanelpopup">
        <group_colors>
          <color name="link_text">
            <fill type="linear" rotation="90">
              <colors>
                <color rgb="0xFF0000" alpha="100" stop="0" />
              </colors>
            </fill>
          </color>
          <color name="link_hover">
            <fill type="linear" rotation="90">
              <colors>
                <color rgb="0xFFFFFF" alpha="100" stop="0" />
              </colors>
            </fill>
          </color>
          <color name="bg">
            <fill type="linear" rotation="90">
              <colors>
                <color rgb="0x000000" alpha="0" stop="0" />
              </colors>
            </fill>
          </color>
          <color name="shadow">
            <fill type="linear" rotation="90">
              <colors>
                <color rgb="0x000000" alpha="0" stop="0" />
              </colors>
            </fill>
          </color>
          <color name="name_text">
            <fill type="linear" rotation="90">
              <colors>
                <color rgb="0xFFFFFF" alpha="100" stop="0" />
              </colors>
            </fill>
          </color>
          <color name="bio_text">
            <fill type="linear" rotation="90">
              <colors>
                <color rgb="0xBABBBA" alpha="100" stop="0" />
              </colors>
            </fill>
          </color>
        </group_colors>
      </color_group>
      <color_group name="timer">
        <group_colors>
          <color name="duration">
            <fill type="linear" rotation="90">
              <colors>
                <color rgb="0x3C3C3C" alpha="100" stop="0" />
              </colors>
            </fill>
          </color>
          <color name="elapsed">
            <fill type="linear" rotation="90">
              <colors>
                <color rgb="0xFEE347" alpha="100" stop="0" />
              </colors>
            </fill>
          </color>
          <color name="stroke">
            <fill type="linear" rotation="90">
              <colors>
                <color rgb="0xC7C7C7" alpha="100" stop="0" />
              </colors>
            </fill>
          </color>
          <color name="inner">
            <fill type="linear" rotation="90">
              <colors>
                <color rgb="0xFFFFFF" alpha="100" stop="0" />
              </colors>
            </fill>
          </color>
          <color name="text">
            <fill type="linear" rotation="90">
              <colors>
                <color rgb="0xBABBBA" alpha="100" stop="0" />
              </colors>
            </fill>
          </color>
        </group_colors>
      </color_group>
      <color_group name="window">
        <group_colors>
          <color name="text">
            <fill type="linear" rotation="90">
              <colors>
                <color rgb="0xF8F8F8" alpha="100" stop="0" />
              </colors>
            </fill>
          </color>
          <color name="btn_text">
            <fill type="linear" rotation="90">
              <colors>
                <color rgb="0xF8F8F8" alpha="100" stop="0" />
              </colors>
            </fill>
          </color>
          <color name="inner">
            <fill type="linear" rotation="90">
              <colors>
                <color rgb="0x316300" alpha="0" stop="0" />
              </colors>
            </fill>
          </color>
          <color name="bg">
            <fill type="linear" rotation="90">
              <colors>
                <color rgb="0x212121" alpha="100" stop="0" />
              </colors>
            </fill>
          </color>
          <color name="diva">
            <fill type="linear" rotation="90">
              <colors>
                <color rgb="0x4E4E4E" alpha="100" stop="0" />
              </colors>
            </fill>
          </color>
          <color name="divb">
            <fill type="linear" rotation="90">
              <colors>
                <color rgb="0x4E4E4E" alpha="0" stop="0" />
              </colors>
            </fill>
          </color>
          <color name="shadow">
            <fill type="linear" rotation="90">
              <colors>
                <color rgb="0x000000" alpha="20" stop="0" />
              </colors>
            </fill>
          </color>
          <color name="border">
            <fill type="linear" rotation="90">
              <colors>
                <color rgb="0x454545" alpha="100" stop="0" />
              </colors>
            </fill>
          </color>
          <color name="separator">
            <fill type="linear" rotation="90">
              <colors>
                <color rgb="0xFFFFFF" alpha="100" stop="0" />
              </colors>
            </fill>
          </color>
          <color name="selected_border">
            <fill type="linear" rotation="90">
              <colors>
                <color rgb="0xFFFFFF" alpha="100" stop="0" />
              </colors>
            </fill>
          </color>
        </group_colors>
      </color_group>
      <color_group name="editor">
        <group_colors>
          <color name="slide_text">
            <fill type="linear" rotation="90">
              <colors>
                <color rgb="0xE2E2E2" alpha="100" stop="0" />
              </colors>
            </fill>
          </color>
          <color name="html_text">
            <fill type="linear" rotation="90">
              <colors>
                <color rgb="0xBABBBA" alpha="100" stop="0" />
              </colors>
            </fill>
          </color>
          <color name="btn_text_shadow">
            <fill type="linear" rotation="90">
              <colors>
                <color rgb="0x000000" alpha="0" stop="0" />
              </colors>
            </fill>
          </color>
          <color name="btn_text">
            <fill type="linear" rotation="90">
              <colors>
                <color rgb="0xFFFFFF" alpha="100" stop="0" />
              </colors>
            </fill>
          </color>
          <color name="btn_border">
            <fill type="linear" rotation="90">
              <colors>
                <color rgb="0xD3D3D3" alpha="100" stop="0" />
              </colors>
            </fill>
          </color>
          <color name="btn_hover">
            <fill type="linear" rotation="90">
              <colors>
                <color rgb="0x444444" alpha="100" stop="0" />
              </colors>
            </fill>
          </color>
          <color name="btn_down">
            <fill type="linear" rotation="90">
              <colors>
                <color rgb="0x444444" alpha="100" stop="0" />
              </colors>
            </fill>
          </color>
          <color name="btn_bg">
            <fill type="linear" rotation="90">
              <colors>
                <color rgb="0x222222" alpha="100" stop="0" />
              </colors>
            </fill>
          </color>
        </group_colors>
      </color_group>
      <color_group name="listitem">
        <group_colors>
          <color name="scene_text">
            <fill type="linear" rotation="90">
              <colors>
                <color rgb="0xF8F8F8" alpha="100" stop="0" />
              </colors>
            </fill>
          </color>
          <color name="selected_text">
            <fill type="linear" rotation="90" />
          </color>
          <color name="shadow">
            <fill type="linear" rotation="90" />
          </color>
          <color name="selected">
            <fill type="linear" rotation="90" />
          </color>
          <color name="text">
            <fill type="linear" rotation="90">
              <colors>
                <color rgb="0xBABBBA" alpha="100" stop="0" />
              </colors>
            </fill>
          </color>
          <color name="viewed">
            <fill type="linear" rotation="90">
              <colors>
                <color rgb="0xBABBBA" alpha="100" stop="0" />
              </colors>
            </fill>
          </color>
          <color name="hover">
            <fill type="linear" rotation="90">
              <colors>
                <color rgb="0xFFFFFF" alpha="6" stop="0" />
              </colors>
            </fill>
          </color>
          <color name="lines">
            <fill type="linear" rotation="90" />
          </color>
          <color name="selected_hover_border">
            <fill type="linear" rotation="90">
              <colors>
                <color rgb="0x6C6C6C" alpha="100" stop="0" />
              </colors>
            </fill>
          </color>
        </group_colors>
      </color_group>
      <color_group name="glossary">
        <group_colors>
          <color name="selected_text">
            <fill type="linear" rotation="90">
              <colors>
                <color rgb="0xFFFFFF" alpha="100" stop="0" />
              </colors>
            </fill>
          </color>
          <color name="selected">
            <fill type="linear" rotation="90">
              <colors>
                <color rgb="0xFFFFFF" alpha="100" stop="0" />
              </colors>
            </fill>
          </color>
          <color name="text">
            <fill type="linear" rotation="90">
              <colors>
                <color rgb="0xBABBBA" alpha="100" stop="0" />
              </colors>
            </fill>
          </color>
          <color name="hover">
            <fill type="linear" rotation="90">
              <colors>
                <color rgb="0xBABBBA" alpha="100" stop="0" />
              </colors>
            </fill>
          </color>
          <color name="heading_text">
            <fill type="linear" rotation="90">
              <colors>
                <color rgb="0xF8F8F8" alpha="100" stop="0" />
              </colors>
            </fill>
          </color>
          <color name="diva">
            <fill type="linear" rotation="90">
              <colors>
                <color rgb="0x000000" alpha="0" stop="0" />
              </colors>
            </fill>
          </color>
          <color name="divb">
            <fill type="linear" rotation="90">
              <colors>
                <color rgb="0x000000" alpha="0" stop="0" />
              </colors>
            </fill>
          </color>
          <color name="divc">
            <fill type="linear" rotation="90">
              <colors>
                <color rgb="0x000000" alpha="0" stop="0" />
              </colors>
            </fill>
          </color>
          <color name="bg">
            <fill type="linear" rotation="90">
              <colors>
                <color rgb="0x000000" alpha="0" stop="0" />
              </colors>
            </fill>
          </color>
        </group_colors>
      </color_group>
      <color_group name="notes">
        <group_colors>
          <color name="text">
            <fill type="linear" rotation="90">
              <colors>
                <color rgb="0xBABBBA" alpha="100" stop="0" />
              </colors>
            </fill>
          </color>
        </group_colors>
      </color_group>
      <color_group name="resource">
        <group_colors>
          <color name="separator">
            <fill type="linear" rotation="90">
              <colors>
                <color rgb="0x000000" alpha="0" stop="0" />
              </colors>
            </fill>
          </color>
          <color name="hover">
            <fill type="linear" rotation="90">
              <colors>
                <color rgb="0xFFFFFF" alpha="6" stop="0" />
              </colors>
            </fill>
          </color>
        </group_colors>
      </color_group>
      <color_group name="outline">
        <group_colors>
          <color name="search_hover">
            <fill type="linear" rotation="90">
              <colors>
                <color rgb="0x000000" alpha="0" stop="0" />
              </colors>
            </fill>
          </color>
          <color name="search_text">
            <fill type="linear" rotation="90">
              <colors>
                <color rgb="0x2D2D2D" alpha="100" stop="0" />
              </colors>
            </fill>
          </color>
          <color name="divc">
            <fill type="linear" rotation="90">
              <colors>
                <color rgb="0x000000" alpha="0" stop="0" />
              </colors>
            </fill>
          </color>
          <color name="divb">
            <fill type="linear" rotation="90">
              <colors>
                <color rgb="0x000000" alpha="0" stop="0" />
              </colors>
            </fill>
          </color>
          <color name="diva">
            <fill type="linear" rotation="90">
              <colors>
                <color rgb="0x000000" alpha="0" stop="0" />
              </colors>
            </fill>
          </color>
        </group_colors>
      </color_group>
      <color_group name="transcript">
        <group_colors>
          <color name="heading_text">
            <fill type="linear" rotation="90">
              <colors>
                <color rgb="0xFFFFFF" alpha="100" stop="0" />
              </colors>
            </fill>
          </color>
          <color name="div">
            <fill type="linear" rotation="90">
              <colors>
                <color rgb="0x000000" alpha="0" stop="0" />
              </colors>
            </fill>
          </color>
        </group_colors>
      </color_group>
      <color_group name="tabs">
        <group_colors>
          <color name="shadow">
            <fill type="linear" rotation="90">
              <colors>
                <color rgb="0x000000" alpha="0" stop="0" />
              </colors>
            </fill>
          </color>
          <color name="hover">
            <fill type="linear" rotation="90">
              <colors>
                <color rgb="0xF8F8F8" alpha="100" stop="0" />
              </colors>
            </fill>
          </color>
          <color name="selected">
            <fill type="linear" rotation="90">
              <colors>
                <color rgb="0xF8F8F8" alpha="100" stop="0" />
              </colors>
            </fill>
          </color>
          <color name="text">
            <fill type="linear" rotation="90">
              <colors>
                <color rgb="0xBABBBA" alpha="100" stop="0" />
              </colors>
            </fill>
          </color>
          <color name="bg">
            <fill type="linear" rotation="90">
              <colors>
                <color rgb="0x000000" alpha="0" stop="0" />
              </colors>
            </fill>
          </color>
          <color name="panel_bg">
            <fill type="linear" rotation="90">
              <colors>
                <color rgb="0x212121" alpha="100" stop="0" />
              </colors>
            </fill>
          </color>
          <color name="bottom_border">
            <fill type="linear" rotation="90">
              <colors>
                <color rgb="0x6C6C6C" alpha="100" stop="0" />
              </colors>
            </fill>
          </color>
        </group_colors>
      </color_group>
      <color_group name="seekcontrol">
        <group_colors>
          <color name="btn_icon_color">
            <fill type="linear" rotation="90">
              <colors>
                <color rgb="0xB4B4B4" alpha="100" stop="0" />
              </colors>
            </fill>
          </color>
          <color name="seek_position">
            <fill type="linear" rotation="90">
              <colors>
                <color rgb="0xFFFFFF" alpha="60" stop="0" />
              </colors>
            </fill>
          </color>
          <color name="seek_bg">
            <fill type="linear" rotation="90">
              <colors>
                <color rgb="0x6C6C6C" alpha="100" stop="0" />
              </colors>
            </fill>
          </color>
          <color name="seek_border">
            <fill type="linear" rotation="90">
              <colors>
                <color rgb="0x000000" alpha="0" stop="0" />
              </colors>
            </fill>
          </color>
          <color name="border">
            <fill type="linear" rotation="90">
              <colors>
                <color rgb="0x000000" alpha="0" stop="0" />
              </colors>
            </fill>
          </color>
          <color name="bg">
            <fill type="linear" rotation="90">
              <colors>
                <color rgb="0x000000" alpha="0" stop="0" />
              </colors>
            </fill>
          </color>
          <color name="btn_icon_hover">
            <fill type="linear" rotation="90">
              <colors>
                <color rgb="0xFFFFFF" alpha="100" stop="0" />
              </colors>
            </fill>
          </color>
          <color name="btn_icon_shadow">
            <fill type="linear" rotation="90">
              <colors>
                <color rgb="0x000000" alpha="0" stop="0" />
              </colors>
            </fill>
          </color>
        </group_colors>
      </color_group>
      <color_group name="searchinput">
        <group_colors>
          <color name="text_active">
            <fill type="linear" rotation="90">
              <colors>
                <color rgb="0xF8F8F8" alpha="100" stop="0" />
              </colors>
            </fill>
          </color>
          <color name="bg_active">
            <fill type="linear" rotation="90">
              <colors>
                <color rgb="0x292929" alpha="100" stop="0" />
              </colors>
            </fill>
          </color>
          <color name="search_text">
            <fill type="linear" rotation="90">
              <colors>
                <color rgb="0xBABBBA" alpha="100" stop="0" />
              </colors>
            </fill>
          </color>
          <color name="hover_glow">
            <fill type="linear" rotation="90">
              <colors>
                <color rgb="0x457E13" alpha="0" stop="0" />
              </colors>
            </fill>
          </color>
          <color name="button_hover">
            <fill type="linear" rotation="90">
              <colors>
                <color rgb="0x3F8500" alpha="100" stop="0" />
              </colors>
            </fill>
          </color>
          <color name="icon">
            <fill type="linear" rotation="90">
              <colors>
                <color rgb="0xBABBBA" alpha="100" stop="0" />
              </colors>
            </fill>
          </color>
          <color name="border">
            <fill type="linear" rotation="90">
              <colors>
                <color rgb="0x000000" alpha="0" stop="0" />
              </colors>
            </fill>
          </color>
          <color name="outer_border">
            <fill type="linear" rotation="90">
              <colors>
                <color rgb="0x6C6C6C" alpha="100" stop="0" />
              </colors>
            </fill>
          </color>
          <color name="bg">
            <fill type="linear" rotation="90">
              <colors>
                <color rgb="0xFFFFFF" alpha="6" stop="0" />
              </colors>
            </fill>
          </color>
          <color name="bg_in_tab">
            <fill type="linear" rotation="90">
              <colors>
                <color rgb="0x545454" alpha="100" stop="0" />
              </colors>
            </fill>
          </color>
        </group_colors>
      </color_group>
      <color_group name="scrollarea">
        <group_colors>
          <color name="detailb">
            <fill type="linear" rotation="90">
              <colors>
                <color rgb="0x6AA242" alpha="100" stop="0" />
              </colors>
            </fill>
          </color>
          <color name="detaila">
            <fill type="linear" rotation="90">
              <colors>
                <color rgb="0x2A5400" alpha="100" stop="0" />
              </colors>
            </fill>
          </color>
          <color name="shadow">
            <fill type="linear" rotation="90">
              <colors>
                <color rgb="0x275000" alpha="100" stop="0" />
              </colors>
            </fill>
          </color>
          <color name="icons">
            <fill type="linear" rotation="90">
              <colors>
                <color rgb="0xFFFFFF" alpha="100" stop="0" />
              </colors>
            </fill>
          </color>
          <color name="button_border">
            <fill type="linear" rotation="90">
              <colors>
                <color rgb="0x2A5500" alpha="100" stop="0" />
              </colors>
            </fill>
          </color>
          <color name="button_inner">
            <fill type="linear" rotation="90">
              <colors>
                <color rgb="0x4B8A16" alpha="100" stop="0" />
              </colors>
            </fill>
          </color>
          <color name="button_bg">
            <fill type="linear" rotation="90">
              <colors>
                <color rgb="0xB3B4B3" alpha="75" stop="0" />
              </colors>
            </fill>
          </color>
          <color name="button_bg_hover">
            <fill type="linear" rotation="90">
              <colors>
                <color rgb="0xB3B4B3" alpha="75" stop="0" />
              </colors>
            </fill>
          </color>
          <color name="border">
            <fill type="linear" rotation="90">
              <colors>
                <color rgb="0x479901" alpha="100" stop="0" />
              </colors>
            </fill>
          </color>
          <color name="bg">
            <fill type="linear" rotation="0">
              <colors>
                <color rgb="0x366F00" alpha="100" stop="0" />
              </colors>
            </fill>
          </color>
        </group_colors>
      </color_group>
      <color_group name="menu">
        <group_colors>
          <color name="shadow">
            <fill type="linear" rotation="90">
              <colors>
                <color rgb="0x000000" alpha="0" stop="0" />
              </colors>
            </fill>
          </color>
          <color name="bg">
            <fill type="linear" rotation="90">
              <colors>
                <color rgb="0x212121" alpha="100" stop="0" />
              </colors>
            </fill>
          </color>
          <color name="generic_shadow">
            <fill type="linear" rotation="90">
              <colors>
                <color rgb="0x000000" alpha="94" stop="0" />
              </colors>
            </fill>
          </color>
          <color name="right_shadow">
            <fill type="linear" rotation="0">
              <colors>
                <color rgb="0x000000" alpha="0" stop="0" />
                <color rgb="0x000000" alpha="30" stop="255" />
              </colors>
            </fill>
          </color>
          <color name="border">
            <fill type="linear" rotation="90">
              <colors>
                <color rgb="0x454545" alpha="100" stop="0" />
              </colors>
            </fill>
          </color>
        </group_colors>
      </color_group>
      <color_group name="logo">
        <group_colors>
          <color name="shadow">
            <fill type="linear" rotation="90">
              <colors>
                <color rgb="0x254B00" alpha="100" stop="0" />
              </colors>
            </fill>
          </color>
          <color name="bg">
            <fill type="linear" rotation="90">
              <colors>
                <color rgb="0xFFFFFF" alpha="0" stop="0" />
              </colors>
            </fill>
          </color>
        </group_colors>
      </color_group>
      <color_group name="checkbox">
        <group_colors>
          <color name="hover">
            <fill type="linear" rotation="90">
              <colors>
                <color rgb="0xAFDD82" alpha="100" stop="0" />
              </colors>
            </fill>
          </color>
          <color name="text">
            <fill type="linear" rotation="90">
              <colors>
                <color rgb="0xFFFFFF" alpha="100" stop="0" />
              </colors>
            </fill>
          </color>
          <color name="check">
            <fill type="linear" rotation="90">
              <colors>
                <color rgb="0x2BC400" alpha="100" stop="0" />
              </colors>
            </fill>
          </color>
          <color name="bg">
            <fill type="linear" rotation="90">
              <colors>
                <color rgb="0xFFFFFF" alpha="100" stop="0" />
              </colors>
            </fill>
          </color>
          <color name="border">
            <fill type="linear" rotation="90">
              <colors>
                <color rgb="0x2A5300" alpha="100" stop="0" />
              </colors>
            </fill>
          </color>
        </group_colors>
      </color_group>
      <color_group name="button">
        <group_colors>
          <color name="btn_icon_color">
            <fill type="linear" rotation="90">
              <colors>
                <color rgb="0xBABBBA" alpha="100" stop="0" />
              </colors>
            </fill>
          </color>
          <color name="btn_text_shadow">
            <fill type="linear" rotation="90">
              <colors>
                <color rgb="0x000000" alpha="0" stop="0" />
              </colors>
            </fill>
          </color>
          <color name="btn_text">
            <fill type="linear" rotation="90">
              <colors>
                <color rgb="0xBABBBA" alpha="100" stop="0" />
              </colors>
            </fill>
          </color>
          <color name="btn_border">
            <fill type="linear" rotation="90">
              <colors>
                <color rgb="0x000000" alpha="0" stop="0" />
              </colors>
            </fill>
          </color>
          <color name="btn_hover">
            <fill type="linear" rotation="90">
              <colors>
                <color rgb="0xF8F8F8" alpha="100" stop="0" />
              </colors>
            </fill>
          </color>
          <color name="btn_down">
            <fill type="linear" rotation="90">
              <colors>
                <color rgb="0x000000" alpha="0" stop="0" />
              </colors>
            </fill>
          </color>
          <color name="btn_bg">
            <fill type="linear" rotation="90">
              <colors>
                <color rgb="0x000000" alpha="0" stop="0" />
              </colors>
            </fill>
          </color>
          <color name="btn_glow">
            <fill type="linear" rotation="90">
              <colors>
                <color rgb="0x000000" alpha="0" stop="0" />
              </colors>
            </fill>
          </color>
          <color name="btn_on_dark_background">
            <fill type="linear" rotation="90">
              <colors>
                <color rgb="0xBABBBA" alpha="100" stop="0" />
              </colors>
            </fill>
          </color>
          <color name="btn_on_dark_background_hover">
            <fill type="linear" rotation="90">
              <colors>
                <color rgb="0xF8F8F8" alpha="100" stop="0" />
              </colors>
            </fill>
          </color>
        </group_colors>
      </color_group>
      <color_group name="base">
        <group_colors>
          <color name="brandhighlight">
            <fill type="linear" rotation="90">
              <colors>
                <color rgb="0x4FBDF4" alpha="100" stop="0" />
              </colors>
            </fill>
          </color>
          <color name="brandhighlight_secondary">
            <fill type="linear" rotation="90">
              <colors>
                <color rgb="0xFFFFFF" alpha="100" stop="0" />
              </colors>
            </fill>
          </color>
          <color name="text">
            <fill type="linear" rotation="90">
              <colors>
                <color rgb="0xBABBBA" alpha="100" stop="0" />
              </colors>
            </fill>
          </color>
          <color name="text_hover">
            <fill type="linear" rotation="90">
              <colors>
                <color rgb="0xF8F8F8" alpha="100" stop="0" />
              </colors>
            </fill>
          </color>
          <color name="text_selected">
            <fill type="linear" rotation="90">
              <colors>
                <color rgb="0xF8F8F8" alpha="100" stop="0" />
              </colors>
            </fill>
          </color>
          <color name="diva">
            <fill type="linear" rotation="90">
              <colors>
                <color rgb="0x454545" alpha="100" stop="0" />
              </colors>
            </fill>
          </color>
          <color name="divb">
            <fill type="linear" rotation="90">
              <colors>
                <color rgb="0x000000" alpha="0" stop="0" />
              </colors>
            </fill>
          </color>
          <color name="menu_shade">
            <fill type="linear" rotation="90">
              <colors>
                <color rgb="0x212121" alpha="100" stop="0" />
              </colors>
            </fill>
          </color>
          <color name="border">
            <fill type="linear" rotation="90">
              <colors>
                <color rgb="0x282828" alpha="100" stop="0" />
              </colors>
            </fill>
          </color>
          <color name="bg">
            <fill type="linear" rotation="90">
              <colors>
                <color rgb="0x282828" alpha="100" stop="0" />
              </colors>
            </fill>
          </color>
          <color name="slide_bg">
            <fill type="linear" rotation="90">
              <colors>
                <color rgb="0x282828" alpha="100" stop="0" />
              </colors>
            </fill>
          </color>
          <color name="overlay_message">
            <fill type="linear" rotation="90">
              <colors>
                <color rgb="0x000000" alpha="85" stop="0" />
              </colors>
            </fill>
          </color>
          <color name="selected_bg">
            <fill type="linear" rotation="90">
              <colors>
                <color rgb="0xFFFFFF" alpha="6" stop="0" />
              </colors>
            </fill>
          </color>
          <color name="selected_border">
            <fill type="linear" rotation="90">
              <colors>
                <color rgb="0x6C6C6C" alpha="100" stop="0" />
              </colors>
            </fill>
          </color>
          <color name="separator">
            <fill type="linear" rotation="90">
              <colors>
                <color rgb="0x454545" alpha="100" stop="0" />
              </colors>
            </fill>
          </color>
          <color name="control_border">
            <fill type="linear" rotation="90">
              <colors>
                <color rgb="0x6C6C6C" alpha="100" stop="0" />
              </colors>
            </fill>
          </color>
        </group_colors>
      </color_group>
      <color_group name="settings">
        <group_colors>
          <color name="panel_bg">
            <fill type="linear" rotation="90">
              <colors>
                <color rgb="0x212121" alpha="100" stop="0" />
              </colors>
            </fill>
          </color>
          <color name="panel_shadow">
            <fill type="linear" rotation="90">
              <colors>
                <color rgb="0x000000" alpha="35" stop="0" />
              </colors>
            </fill>
          </color>
          <color name="toggle_border">
            <fill type="linear" rotation="90">
              <colors>
                <color rgb="0x7C7C7C" alpha="100" stop="0" />
              </colors>
            </fill>
          </color>
          <color name="toggle_thumb_off">
            <fill type="linear" rotation="90">
              <colors>
                <color rgb="0xA2A2A2" alpha="100" stop="0" />
              </colors>
            </fill>
          </color>
          <color name="toggle_track_on">
            <fill type="linear" rotation="90">
              <colors>
                <color rgb="0x4FBDF4" alpha="100" stop="0" />
              </colors>
            </fill>
          </color>
          <color name="toggle_track_off">
            <fill type="linear" rotation="90">
              <colors>
                <color rgb="0xFFFFFF" alpha="10" stop="0" />
              </colors>
            </fill>
          </color>
          <color name="toggle_label">
            <fill type="linear" rotation="90">
              <colors>
                <color rgb="0xBABBBA" alpha="100" stop="0" />
              </colors>
            </fill>
          </color>
          <color name="settings_border_color">
            <fill type="linear" rotation="90">
              <colors>
                <color rgb="0x454545" alpha="100" stop="0" />
              </colors>
            </fill>
          </color>
        </group_colors>
      </color_group>
      <color_group name="volume">
        <group_colors>
          <color name="panel_bg">
            <fill type="linear" rotation="90">
              <colors>
                <color rgb="0x212121" alpha="100" stop="0" />
              </colors>
            </fill>
          </color>
          <color name="thumb_border">
            <fill type="linear" rotation="90">
              <colors>
                <color rgb="0x2B5500" alpha="100" stop="0" />
              </colors>
            </fill>
          </color>
          <color name="thumb_inner">
            <fill type="linear" rotation="90">
              <colors>
                <color rgb="0x2B5500" alpha="100" stop="0" />
              </colors>
            </fill>
          </color>
          <color name="thumb_bg">
            <fill type="linear" rotation="90">
              <colors>
                <color rgb="0xFFFFFF" alpha="100" stop="0" />
              </colors>
            </fill>
          </color>
          <color name="slider_border">
            <fill type="linear" rotation="90">
              <colors>
                <color rgb="0x428C01" alpha="100" stop="0" />
              </colors>
            </fill>
          </color>
          <color name="slider_bg">
            <fill type="linear" rotation="0">
              <colors>
                <color rgb="0x6C6C6C" alpha="100" stop="0" />
              </colors>
            </fill>
          </color>
          <color name="slider_shadow">
            <fill type="linear" rotation="90">
              <colors>
                <color rgb="0x000000" alpha="40" stop="0" />
              </colors>
            </fill>
          </color>
          <color name="volume_border_color">
            <fill type="linear" rotation="90">
              <colors>
                <color rgb="0x454545" alpha="100" stop="0" />
              </colors>
            </fill>
          </color>
        </group_colors>
      </color_group>
    </colorscheme>
  </colorschemes>
  <string_tables>
    <string_table name="npnxnanbnsnfns00001100111">
      <string id="three_image_progress_audio">progress</string>
      <string id="three_image_audio">audio</string>
      <string id="three_image_camera_down">camera moved down</string>
      <string id="three_image_camera_left">camera moved left</string>
      <string id="three_image_camera_right">camera moved right</string>
      <string id="three_image_camera_up">camera moved up</string>
      <string id="three_image_interaction_free">free exploration mode</string>
      <string id="three_image_interaction_guided">guided tour mode</string>
      <string id="three_image_hotspot">hotspot</string>
      <string id="three_image_instructions">Use the w, a, s, and d keys to move around the 360 degree image. Press the tab key to jump to interactive markers and hotspots.</string>
      <string id="three_image_interaction">360 degree image interaction</string>
      <string id="three_image_label">label</string>
      <string id="three_image_marker">marker</string>
      <string id="three_image_items">items</string>
      <string id="three_image_interaction_next">next</string>
      <string id="three_image_pause_audio">pause audio</string>
      <string id="three_image_pause_video">pause video</string>
      <string id="three_image_play_audio">play audio</string>
      <string id="three_image_play_video">play video</string>
      <string id="three_image_interaction_prev">previous</string>
      <string id="three_image_visited">visited</string>
      <string id="three_image_of">of</string>
      <string id="three_image_count_of_total">%count% of %total%</string>
      <string id="acc_three_image_step_count_of_total">step %count% of %total%</string>
      <string id="three_image_item">item</string>
      <string id="three_image_interaction_step">step</string>
      <string id="three_image_tooltip">tooltip</string>
      <string id="three_image_total_items">%total% items</string>
      <string id="three_image_total_item">%total% item</string>
      <string id="three_image_progress_video">progress</string>
      <string id="three_image_video">video</string>
      <string id="three_image_video_volume">video volume</string>
      <string id="acc_three_image_count_of_total_items_visited">%count% of %total% items visited</string>
      <string id="acc_three_image_count_of_total_item_visited">%count% of %total% item visited</string>
      <string id="three_image_count_of_total_visited">%count% of %total% visited</string>
      <string id="accessible_text">Accessible text</string>
      <string id="keyboardshortcuts_lower">Keyboard shortcuts</string>
      <string id="zoom_to_fit">Zoom to fit</string>
      <string id="acc_active">active</string>
      <string id="alt_key">Alt</string>
      <string id="check_include">Check to include</string>
      <string id="clear">Clear and return to menu</string>
      <string id="close">Close</string>
      <string id="acc_closed_captions">Closed captions.</string>
      <string id="closed_captions_tip">Toggle captions</string>
      <string id="continue">Continue</string>
      <string id="continueresponsive">Continue</string>
      <string id="ctrl_key">Ctrl</string>
      <string id="enable_keyboardshortcuts">Enable keyboard shortcuts</string>
      <string id="enter_key">Enter</string>
      <string id="exit">Exit</string>
      <string id="filter">Filter</string>
      <string id="finish">FINISH</string>
      <string id="acc_finish">finish</string>
      <string id="definition">Definition</string>
      <string id="acc_definition">definition</string>
      <string id="glossary">Glossary</string>
      <string id="terms">Terms</string>
      <string id="progress_hour">hour</string>
      <string id="progress_hours">hours</string>
      <string id="action">Action</string>
      <string id="keyboardshortcuts">Keyboard Shortcuts</string>
      <string id="shortcuthelp">List keyboard shortcuts</string>
      <string id="mute_shortcut">Mute / unmute</string>
      <string id="next_shortcut">Next slide</string>
      <string id="playpause_shortcut">Play / pause</string>
      <string id="previous_shortcut">Previous slide</string>
      <string id="replay_shortcut">Replay slide</string>
      <string id="shortcut">Shortcut</string>
      <string id="submit_shortcut">Submit slide</string>
      <string id="acctext_shortcut">Toggle accessible text</string>
      <string id="closedcaptions_shortcut">Toggle closed captions</string>
      <string id="togglezoom">Toggle zoom to fit</string>
      <string id="outline">Menu</string>
      <string id="disabled_orientation">Please rotate your device</string>
      <string id="progress_minute">minute</string>
      <string id="progress_minutes">minutes</string>
      <string id="mute_tip">Mute</string>
      <string id="next">NEXT</string>
      <string id="acc_next">next</string>
      <string id="next_slide_tip">Next slide</string>
      <string id="transcript_chk">Notes</string>
      <string id="transcript">Notes</string>
      <string id="bio">Bio</string>
      <string id="more_info">More info</string>
      <string id="closed_captions">Captions</string>
      <string id="acc_pause">pause</string>
      <string id="pause_tip">Pause</string>
      <string id="acc_play">play</string>
      <string id="play_tip">Play</string>
      <string id="send_an_email">Send an email</string>
      <string id="prev">PREV</string>
      <string id="acc_previous">previous</string>
      <string id="previous_slide_tip">Previous slide</string>
      <string id="question_list">Question List</string>
      <string id="replay_tip">Replay</string>
      <string id="acc_replay">replay</string>
      <string id="resources">Resources</string>
      <string id="acc_resources">resources</string>
      <string id="restart">Restart</string>
      <string id="resume">Resume</string>
      <string id="acc_locked">locked</string>
      <string id="acc_search_input">search</string>
      <string id="search_toggle">Search</string>
      <string id="sidebar_toggle">Sidebar Toggle</string>
      <string id="acc_slide_progress">slide progress</string>
      <string id="desktop_start">Start Course</string>
      <string id="mobile_start">Start Course</string>
      <string id="acc_visited">visited</string>
      <string id="search">Search...</string>
      <string id="search_in">Search in:</string>
      <string id="search_results">Search Results</string>
      <string id="progress_second">second</string>
      <string id="progress_seconds">seconds</string>
      <string id="settings_tip">Settings</string>
      <string id="shift_key">Shift</string>
      <string id="acc_skipnavigation">Back to top</string>
      <string id="slide_text_chk">Slide Text</string>
      <string id="spacebar_key">Space</string>
      <string id="submitall">SUBMIT ALL</string>
      <string id="acc_submitall">submit all</string>
      <string id="submit">SUBMIT</string>
      <string id="acc_submit">submit</string>
      <string id="submit_tip">Submit</string>
      <string id="unmute_tip">Unmute</string>
      <string id="acc_volume">volume</string>
    </string_table>
  </string_tables>
  <fonts>
    <font name="Lato">
      <files>
        <file bold="true" italic="false" />
        <file bold="false" italic="false" />
      </files>
    </font>
    <font name="Century Gothic">
      <files>
        <file bold="true" italic="false" />
        <file bold="false" italic="false" />
      </files>
    </font>
    <font name="Tw Cen MT">
      <files>
        <file bold="false" italic="false" />
      </files>
    </font>
    <font name="Articulate Narrow">
      <files>
        <file bold="false" italic="false" />
      </files>
    </font>
    <font name="Arial">
      <files>
        <file bold="true" italic="false" />
        <file bold="false" italic="false" />
      </files>
    </font>
    <font name="Comic Sans MS">
      <files>
        <file bold="true" italic="false" />
      </files>
    </font>
  </fonts>
  <sounds enabled="true" />
  <nav_data>
    <outline>
      <links>
        <slidelink slideid="_player.6Esg3QSRtit" displaytext="PRE  KNOWLEDGE CHECK " expand="true" type="slide">
          <links>
            <slidelink slideid="_player.6Esg3QSRtit.5Yihkwaxeqh" displaytext="Title Screen" expand="false" type="slide" />
            <slidelink slideid="_player.6Esg3QSRtit.5nOKodXsiNt" displaytext="Question 1" expand="false" type="slide" />
            <slidelink slideid="_player.6Esg3QSRtit.5VafhAajRLT" displaytext="Question 2" expand="false" type="slide" />
            <slidelink slideid="_player.6Esg3QSRtit.61hIfdBzLQY" displaytext="Question 3" expand="false" type="slide" />
          </links>
        </slidelink>
        <slidelink slideid="_player.6UlwFiQOBjL" displaytext="TABLE OF CONTENT&amp;amp; LO&amp;apos;s" expand="true" type="slide">
          <links>
            <slidelink slideid="_player.6UlwFiQOBjL.5pUJeO0Txgy" displaytext="Table of content" expand="false" type="slide" />
            <slidelink slideid="_player.6UlwFiQOBjL.5YkqPlJt2Yo" displaytext="Course Objectives" expand="false" type="slide" />
          </links>
        </slidelink>
        <slidelink slideid="_player.6YKdHbCITe9" displaytext="INTRO &amp;amp; TYPES" expand="true" type="slide">
          <links>
            <slidelink slideid="_player.6YKdHbCITe9.6Kl0sDjiHne" displaytext="Introduction" expand="false" type="slide" />
            <slidelink slideid="_player.6YKdHbCITe9.6DoCSZYwBOX" displaytext="Introduction" expand="false" type="slide" />
            <slidelink slideid="_player.6YKdHbCITe9.6TZjQaSGbYG" displaytext="What is sleep?" expand="false" type="slide" />
            <slidelink slideid="_player.6YKdHbCITe9.6qGcPo3iNYn" displaytext="Classification" expand="false" type="slide" />
            <slidelink slideid="_player.6YKdHbCITe9.6XvaoSVTAIM" displaytext="Classification" expand="false" type="slide" />
          </links>
        </slidelink>
        <slidelink slideid="_player.6PNHMTnhP1v" displaytext="SLEEPING POSITIONS" expand="true" type="slide">
          <links>
            <slidelink slideid="_player.6PNHMTnhP1v.6XNN1TCYMx4" displaytext="Sleeping Positions" expand="false" type="slide" />
            <slidelink slideid="_player.6PNHMTnhP1v.5Zrhhk90sql" displaytext="FETAL" expand="false" type="slide" />
            <slidelink slideid="_player.6PNHMTnhP1v.6rauxN0wa5a" displaytext="SOLDIER" expand="false" type="slide" />
            <slidelink slideid="_player.6PNHMTnhP1v.6E32P4X64KM" displaytext="FREE FALL" expand="false" type="slide" />
            <slidelink slideid="_player.6PNHMTnhP1v.6AUyCcUFy6v" displaytext="LEFT" expand="false" type="slide" />
            <slidelink slideid="_player.6PNHMTnhP1v.6JbCtMPbBpW" displaytext="HERON" expand="false" type="slide" />
            <slidelink slideid="_player.6PNHMTnhP1v.6UqXXunOoIg" displaytext="STARFISH" expand="false" type="slide" />
            <slidelink slideid="_player.6PNHMTnhP1v.6GagMXraupb" displaytext="RIGHT" expand="false" type="slide" />
          </links>
        </slidelink>
        <slidelink slideid="_player.5XomhFIOu5j" displaytext="FOOD TO BE AVIODED" expand="true" type="slide">
          <links>
            <slidelink slideid="_player.5XomhFIOu5j.6FBk6TsA0h0" displaytext="Food to be Avioded" expand="false" type="slide" />
          </links>
        </slidelink>
        <slidelink slideid="_player.6WodivaGol5" displaytext="KNOWLEDGE CGECK" expand="true" type="slide">
          <links>
            <slidelink slideid="_player.6WodivaGol5.6hUTERS2Wo4" displaytext="Drag and Drop" expand="false" type="slide" />
            <slidelink slideid="_player.6WodivaGol5.5qdGEhTzJBH" displaytext="Results slide" expand="false" type="slide" />
          </links>
        </slidelink>
      </links>
    </outline>
    <search>
      <slidetext slideid="6Esg3QSRtit.5Yihkwaxeqh" slidebank="false" type="slide">title of the course: sleep disorders before we get started, lets see how much you know about sleep. turn on your audio, enter your name and click on  take quiz to put your knowledge to test. %enteryourname% take quiz take quiz take quiz take quiz take quiz take quiz  title slide 1 / 23      </slidetext>
      <slidetext slideid="6Esg3QSRtit.5nOKodXsiNt" slidebank="false" type="slide">incorrect you did not select the correct response. continue continue continue  correct that's right!  you selected the correct response. continue continue continue   pre  knowledge check q1 2 / 23 why do we sleep? select the response &amp; click on the submit button below. a a no one knows no one knows no one knows b b to ensure proper functioning of our nervous system to ensure proper functioning of our nervous system to ensure proper functioning of our nervous system c c to clean the brain's memory slate to clean the brain's memory slate to clean the brain's memory slate d d to cool the brain to cool the brain to cool the brain      </slidetext>
      <slidetext slideid="6Esg3QSRtit.5VafhAajRLT" slidebank="false" type="slide">incorrect you did not select the correct response. continue continue continue  correct that's right!  you selected the correct response. continue continue continue   pre  knowledge check q2 3 / 23 what is sleep hygiene? select the response &amp; click on the submit button below. a a a bath or shower before bed a bath or shower before bed a bath or shower before bed b b the promotion of regular sleep the promotion of regular sleep the promotion of regular sleep c c the practice of laundering bed linens the practice of laundering bed linens the practice of laundering bed linens d d avoiding emotion before bed avoiding emotion before bed avoiding emotion before bed      </slidetext>
      <slidetext slideid="6Esg3QSRtit.61hIfdBzLQY" slidebank="false" type="slide">incorrect you did not select the correct response. continue continue continue  correct that's right!  you selected the correct response. continue continue continue   pre  knowledge check q3 4 / 23 what is true about sleep? select the response &amp; click on the submit button below. (please select all that apply) a a sleep deprivation can trigger seizures in people with epilepsy. sleep deprivation can trigger seizures in people with epilepsy. sleep deprivation can trigger seizures in people with epilepsy. b b sleep problems occur in almost all people with mental disorders. sleep problems occur in almost all people with mental disorders. sleep problems occur in almost all people with mental disorders. c c extreme sleep deprivation can lead to hallucinations. extreme sleep deprivation can lead to hallucinations. extreme sleep deprivation can lead to hallucinations. d d all of the above all of the above all of the above      </slidetext>
      <slidetext slideid="6UlwFiQOBjL.5pUJeO0Txgy" slidebank="false" type="slide"> table of content 6 / 23        lesson 1 learning outcomes lesson 2 introduction lesson 3 meaning lesson 4 classification of sleep disorders lesson 5 sleeping positions lesson 6 food to be avioded</slidetext>
      <slidetext slideid="6UlwFiQOBjL.5YkqPlJt2Yo" slidebank="false" type="slide">  course objectives       by the end of this course,  youll be able to: define sleep classify sleep disorders examine insomnia &amp; hypersomnia 7 / 23</slidetext>
      <slidetext slideid="6YKdHbCITe9.6Kl0sDjiHne" slidebank="false" type="slide"> introduction     sleep is an important part of your daily routineyou spend about one-third of your time doing it.  quality sleep  and getting enough of it at the right times -- is as essential to survival as food and water.  without sleep you cant form or maintain the pathways in your brain that let you learn and create new memories, and its harder to concentrate and respond quickly.    8 / 23</slidetext>
      <slidetext slideid="6YKdHbCITe9.6DoCSZYwBOX" slidebank="false" type="slide"> a sleep disorder is any condition that involves difficulty experienced when sleeping. such disorders often result in daytime fatigue, causing severe distress and impairment to work, and social or personal functioning. sleep disorders are extremely common in the general population and can lead to significant morbidity. sleep disorders may cause or exacerbate preexisting medical and psychiatric conditions and are associated with high rates of depression, anxiety, and impaired daytime functioning  introduction 9 / 23      </slidetext>
      <slidetext slideid="6YKdHbCITe9.6TZjQaSGbYG" slidebank="false" type="slide">  what is sleep?       sleep is a complex biological process. while you are sleeping, you are unconscious, but your brain and body functions are still active. they are doing a number of important jobs that help you stay healthy and function at your best. so when you don't get enough quality sleep, it does more than just make you feel tired. it can affect your physical and mental health, thinking, and daily functioning. 10 / 23</slidetext>
      <slidetext slideid="6YKdHbCITe9.6qGcPo3iNYn" slidebank="false" type="slide">a tingling or prickly sensation in your legs, along with a powerful urge to move them. a breathing disorder in which you stop breathing for 10 seconds or more during sleep being unable to fall asleep and stay asleep. this is the most common sleep disorder.  sleep disorders       click on each card to know more.  insomnia  insomnia  sleep apnea  sleep apnea restless leg syndrome (rls)  restless leg syndrome (rls)  11 / 23</slidetext>
      <slidetext slideid="6YKdHbCITe9.6XvaoSVTAIM" slidebank="false" type="slide">acting in unusual ways while falling asleep, sleeping, or waking from sleep, such as walking, talking, or eating. problems with the sleep-wake cycle. they make you unable to sleep and wake at the right times. being unable to stay awake during the day. this includes narcolepsy, which causes extreme daytime sleepiness.  sleep disorders        hypersomnia  hypersomnia  circadian rhythm disorders  circadian rhythm disorders  parasomnia  parasomnia click on each card to know more. 12 / 23</slidetext>
      <slidetext slideid="6PNHMTnhP1v.6XNN1TCYMx4" slidebank="false" type="slide"> most common sleeping positions       what your sleeping position says about your mental health? click on each icon to reveal information.   fetal   soldier   free fall   left   heron   starfish   right 13 / 32</slidetext>
      <slidetext slideid="6PNHMTnhP1v.5Zrhhk90sql" slidebank="false" type="slide"> most common sleeping positions         fetal sleepers: warm &amp; conscientious curling up in the fetal position like a newborn baby signals that youre trying to comfort yourself. traits include a soft interior which is camouflaged by a tough exterior, shy but warm, conscientious, organized and ready to face the day. close close close close close close 14 / 23</slidetext>
      <slidetext slideid="6PNHMTnhP1v.6rauxN0wa5a" slidebank="false" type="slide"> most common sleeping positions         back sleepers: high expectations sleeping on your back with your arms by your sides, also known as soldier position, reveals that you have high expectations of yourself and others, and practice personal responsibility. back sleepers are also the more likely to snore. close close close close close close 15 / 23</slidetext>
      <slidetext slideid="6PNHMTnhP1v.6E32P4X64KM" slidebank="false" type="slide"> most common sleeping positions         free fall sleepers: brash &amp; anxious those who sleep on their stomachs with their arms wide are known as free fallers. you are likely to be  brash and outgoing but also harbor feelings of anxiety due to feeling overwhelmed during your waking hours. close close close close close close 16 / 23</slidetext>
      <slidetext slideid="6PNHMTnhP1v.6AUyCcUFy6v" slidebank="false" type="slide"> most common sleeping positions         left side sleepers: creative and curious people who favor sleeping on their left sides are more likely to work in the literary and performing arts, marketing and advertising, and have a high level of education. close close close close close close 17 / 23</slidetext>
      <slidetext slideid="6PNHMTnhP1v.6JbCtMPbBpW" slidebank="false" type="slide"> most common sleeping positions         heron sleeper: unpredictable if you generally sleep with your arms and legs splayed, you're a heron sleeper. heron sleepers are moody,  unpredictable, and have a hard time making decisions. close close close close close close 18 / 23</slidetext>
      <slidetext slideid="6PNHMTnhP1v.6UqXXunOoIg" slidebank="false" type="slide"> most common sleeping positions         starfish sleepers: great friends if you sleep on your back with your arms wide, you're a starfish sleeper. starfish sleeper prefer not to be center of attention, and their keen listening skills make them trusted friends and confidants. close close close close close close 19 / 23</slidetext>
      <slidetext slideid="6PNHMTnhP1v.6GagMXraupb" slidebank="false" type="slide"> most common sleeping positions         right side sleepers: risk and rewards right side sleepers were more likely to take risk. they are more likely to consume caffeine, gamble and challenge norms. right side sleepers are attracted to logistics, transportation, and entrepreneurial pursuits. close close close close close close 20  / 23 click on arrow to proceed next.</slidetext>
      <slidetext slideid="5XomhFIOu5j.6FBk6TsA0h0" slidebank="false" type="slide"> food to be avioded       want some good sleep?  then avoid the following food.        coffee    alcohol    chocolate           heavy food  21 / 23</slidetext>
      <slidetext slideid="6WodivaGol5.6hUTERS2Wo4" slidebank="false" type="slide">incorrect you did not select the correct response.  correct that's right!  you selected the correct response.   knowledge check       22 / 23 match the following: drag the numbers &amp; drop it near to the appropriate sleep position  then click on submit button below. fetal sleepers back sleepers free fall sleepers left side sleepers right side sleepers creative and curious warm &amp; conscientious high expectations brash &amp; anxious risk and rewards 1 1 1 2 2 2 3 3 3 4 4 4 5 5 5</slidetext>
      <slidetext slideid="6WodivaGol5.5qdGEhTzJBH" slidebank="false" type="slide"> knowledge check  result slide 23 / 23       fetal sleepers back sleepers free fall sleepers left side sleepers right side sleepers creative and curious warm &amp; conscientious high expectations brash &amp; anxious risk and rewards match the following: drag the numbers &amp; drop it near to the appropriate sleep position  then click on submit button below. 1 1 1 2 2 2 3 3 3 4 4 4 5 5 5</slidetext>
    </search>
  </nav_data>
  <resource_data description="&lt;p align='left'&gt;&lt;font face='Lato' style='font-size: 11px;' size='11' color='#BABBBA'&gt;Here are some useful links and documents:&lt;/font&gt;&lt;/p&gt;" />
  <transcript_data>
    <slidetranscripts>
      <slidetranscript slideid="6Esg3QSRtit.5Yihkwaxeqh" slidebank="false" type="slide" noteswf="" notespng="" pathlib="Lib" pathindex="0">&lt;Document xmlns:xsi="http://www.w3.org/2001/XMLSchema-instance" xmlns:xsd="http://www.w3.org/2001/XMLSchema"&gt;
  &lt;Content&gt;
    &lt;Block&gt;
      &lt;Style Justification="Left" /&gt;
      &lt;Span Text="TITLE OF THE COURSE:&amp;#xA;"&gt;
        &lt;Style FontFamily="Century Gothic" FontSize="10.5" FontIsBold="True" ForegroundColor="#F19951" LinkColor="#F19951" /&gt;
      &lt;/Span&gt;
    &lt;/Block&gt;
    &lt;Block&gt;
      &lt;Style Justification="Left" /&gt;
      &lt;Span Text="SLEEP DISORDERS&amp;#xA;"&gt;
        &lt;Style FontFamily="Century Gothic" FontIsBold="True" ForegroundColor="#F19951" LinkColor="#F19951" /&gt;
      &lt;/Span&gt;
    &lt;/Block&gt;
    &lt;Block&gt;
      &lt;Style Justification="Left" /&gt;
      &lt;Span Text="&amp;#xA;"&gt;
        &lt;Style FontFamily="Century Gothic" FontIsBold="True" ForegroundColor="#F19951" LinkColor="#F19951" /&gt;
      &lt;/Span&gt;
    &lt;/Block&gt;
    &lt;Block&gt;
      &lt;Style Justification="Right" /&gt;
      &lt;Span Text="Before we get started, lets see how much you know about sleep. Enter your name and click on  Take Quiz to put your knowledge to test."&gt;
        &lt;Style FontFamily="Century Gothic" ForegroundColor="lt1,00" LinkColor="lt1,00" /&gt;
      &lt;/Span&gt;
      &lt;Span Text="&amp;#xA;"&gt;
        &lt;Style FontFamily="Century Gothic" FontIsBold="True" ForegroundColor="#F19951" LinkColor="#F19951" /&gt;
      &lt;/Span&gt;
    &lt;/Block&gt;
    &lt;Block&gt;
      &lt;Style Justification="Left" /&gt;
    &lt;/Block&gt;
  &lt;/Content&gt;
&lt;/Document&gt;</slidetranscript>
      <slidetranscript slideid="6Esg3QSRtit.5nOKodXsiNt" slidebank="false" type="slide" noteswf="" notespng="" pathlib="Lib" pathindex="1">&lt;Document xmlns:xsi="http://www.w3.org/2001/XMLSchema-instance" xmlns:xsd="http://www.w3.org/2001/XMLSchema"&gt;
  &lt;Content&gt;
    &lt;Block&gt;
      &lt;Style /&gt;
      &lt;Span Text="Question 1&amp;#xA;"&gt;
        &lt;Style FontFamily="Century Gothic" FontIsBold="True" ForegroundColor="lt1,00" LinkColor="lt1,00" /&gt;
      &lt;/Span&gt;
    &lt;/Block&gt;
    &lt;Block&gt;
      &lt;Style /&gt;
      &lt;Span Text="&amp;#xA;"&gt;
        &lt;Style FontFamily="Century Gothic" FontIsBold="True" ForegroundColor="lt1,00" LinkColor="lt1,00" /&gt;
      &lt;/Span&gt;
    &lt;/Block&gt;
    &lt;Block&gt;
      &lt;Style /&gt;
      &lt;Span Text="WHY DO WE SLEEP?"&gt;
        &lt;Style FontFamily="Century Gothic" FontIsBold="True" ForegroundColor="lt1,00" LinkColor="lt1,00" /&gt;
      &lt;/Span&gt;
    &lt;/Block&gt;
  &lt;/Content&gt;
&lt;/Document&gt;</slidetranscript>
      <slidetranscript slideid="6Esg3QSRtit.5VafhAajRLT" slidebank="false" type="slide" noteswf="" notespng="" pathlib="Lib" pathindex="2">&lt;Document xmlns:xsi="http://www.w3.org/2001/XMLSchema-instance" xmlns:xsd="http://www.w3.org/2001/XMLSchema"&gt;
  &lt;Content&gt;
    &lt;Block&gt;
      &lt;Style /&gt;
      &lt;Span Text="WHAT IS SLEEP HYGIENE?&amp;#xA;"&gt;
        &lt;Style FontFamily="Century Gothic" FontIsBold="True" ForegroundColor="lt1,00" LinkColor="lt1,00" /&gt;
      &lt;/Span&gt;
    &lt;/Block&gt;
    &lt;Block&gt;
      &lt;Style /&gt;
      &lt;Span Text="&amp;#xA;"&gt;
        &lt;Style FontFamily="Century Gothic" FontIsBold="True" ForegroundColor="lt1,00" LinkColor="lt1,00" /&gt;
      &lt;/Span&gt;
    &lt;/Block&gt;
    &lt;Block&gt;
      &lt;Style /&gt;
      &lt;Span Text="Select the response &amp;amp; Click on the Submit button below."&gt;
        &lt;Style FontFamily="Century Gothic" FontSize="12" FontIsBold="True" ForegroundColor="lt1,00" LinkColor="lt1,00" /&gt;
      &lt;/Span&gt;
      &lt;Span Text="&amp;#xA;"&gt;
        &lt;Style FontFamily="Century Gothic" FontIsBold="True" ForegroundColor="lt1,00" LinkColor="lt1,00" /&gt;
      &lt;/Span&gt;
    &lt;/Block&gt;
    &lt;Block&gt;
      &lt;Style /&gt;
      &lt;Span Text="&amp;#xA;"&gt;
        &lt;Style FontFamily="Century Gothic" FontIsBold="True" ForegroundColor="lt1,00" LinkColor="lt1,00" /&gt;
      &lt;/Span&gt;
    &lt;/Block&gt;
    &lt;Block&gt;
      &lt;Style /&gt;
      &lt;Span Text=""&gt;
        &lt;Style FontFamily="Century Gothic" FontIsBold="True" ForegroundColor="lt1,00" LinkColor="lt1,00" /&gt;
      &lt;/Span&gt;
    &lt;/Block&gt;
  &lt;/Content&gt;
&lt;/Document&gt;</slidetranscript>
      <slidetranscript slideid="6Esg3QSRtit.61hIfdBzLQY" slidebank="false" type="slide" noteswf="" notespng="" pathlib="Lib" pathindex="3">&lt;Document xmlns:xsi="http://www.w3.org/2001/XMLSchema-instance" xmlns:xsd="http://www.w3.org/2001/XMLSchema"&gt;
  &lt;Content&gt;
    &lt;Block&gt;
      &lt;Style /&gt;
      &lt;Span Text="QUESTION 3&amp;#xA;"&gt;
        &lt;Style FontFamily="Century Gothic" FontIsBold="True" ForegroundColor="lt1,00" LinkColor="lt1,00" /&gt;
      &lt;/Span&gt;
    &lt;/Block&gt;
    &lt;Block&gt;
      &lt;Style /&gt;
      &lt;Span Text="&amp;#xA;"&gt;
        &lt;Style FontFamily="Century Gothic" FontIsBold="True" ForegroundColor="lt1,00" LinkColor="lt1,00" /&gt;
      &lt;/Span&gt;
    &lt;/Block&gt;
    &lt;Block&gt;
      &lt;Style /&gt;
      &lt;Span Text="WHAT IS TRUE ABOUT SLEEP?&amp;#xA;"&gt;
        &lt;Style FontFamily="Century Gothic" FontIsBold="True" ForegroundColor="lt1,00" LinkColor="lt1,00" /&gt;
      &lt;/Span&gt;
    &lt;/Block&gt;
    &lt;Block&gt;
      &lt;Style /&gt;
      &lt;Span Text="&amp;#xA;"&gt;
        &lt;Style FontFamily="Century Gothic" FontIsBold="True" ForegroundColor="lt1,00" LinkColor="lt1,00" /&gt;
      &lt;/Span&gt;
    &lt;/Block&gt;
    &lt;Block&gt;
      &lt;Style /&gt;
      &lt;Span Text="Select the response &amp;amp; Click on the Submit button below. (Please select all that apply)"&gt;
        &lt;Style FontFamily="Century Gothic" FontSize="12" FontIsBold="True" ForegroundColor="lt1,00" LinkColor="lt1,00" /&gt;
      &lt;/Span&gt;
    &lt;/Block&gt;
  &lt;/Content&gt;
&lt;/Document&gt;</slidetranscript>
      <slidetranscript slideid="6UlwFiQOBjL.5YkqPlJt2Yo" slidebank="false" type="slide" noteswf="" notespng="" pathlib="Lib" pathindex="4">&lt;Document xmlns:xsi="http://www.w3.org/2001/XMLSchema-instance" xmlns:xsd="http://www.w3.org/2001/XMLSchema"&gt;
  &lt;Content&gt;
    &lt;Block&gt;
      &lt;Style /&gt;
      &lt;Span Text="By the end of this course, &amp;#xA;"&gt;
        &lt;Style FontFamily="Century Gothic" FontIsBold="True" ForegroundColor="lt1,00" LinkColor="lt1,00" /&gt;
      &lt;/Span&gt;
    &lt;/Block&gt;
    &lt;Block&gt;
      &lt;Style /&gt;
      &lt;Span Text="youll be able to:&amp;#xA;"&gt;
        &lt;Style FontFamily="Century Gothic" FontIsBold="True" ForegroundColor="lt1,00" LinkColor="lt1,00" /&gt;
      &lt;/Span&gt;
    &lt;/Block&gt;
    &lt;Block&gt;
      &lt;Style /&gt;
      &lt;Span Text="&amp;#xA;"&gt;
        &lt;Style FontFamily="Century Gothic" FontIsBold="True" ForegroundColor="lt1,00" LinkColor="lt1,00" /&gt;
      &lt;/Span&gt;
    &lt;/Block&gt;
    &lt;Block&gt;
      &lt;Style Justification="Left" /&gt;
      &lt;Span Text="Define Sleep&amp;#xA;"&gt;
        &lt;Style FontFamily="Tw Cen MT" FontSize="16" ForegroundColor="lt1,00" LinkColor="lt1,00" /&gt;
      &lt;/Span&gt;
    &lt;/Block&gt;
    &lt;Block&gt;
      &lt;Style Justification="Left" /&gt;
      &lt;Span Text="Classify Sleep Disorders&amp;#xA;"&gt;
        &lt;Style FontFamily="Tw Cen MT" FontSize="16" ForegroundColor="lt1,00" LinkColor="lt1,00" /&gt;
      &lt;/Span&gt;
    &lt;/Block&gt;
    &lt;Block&gt;
      &lt;Style Justification="Left" /&gt;
      &lt;Span Text="Examine Insomnia &amp;amp; Hypersomnia"&gt;
        &lt;Style FontFamily="Tw Cen MT" FontSize="16" ForegroundColor="lt1,00" LinkColor="lt1,00" /&gt;
      &lt;/Span&gt;
      &lt;Span Text="&amp;#xA;"&gt;
        &lt;Style FontFamily="Century Gothic" FontIsBold="True" ForegroundColor="lt1,00" LinkColor="lt1,00" /&gt;
      &lt;/Span&gt;
    &lt;/Block&gt;
    &lt;Block&gt;
      &lt;Style /&gt;
    &lt;/Block&gt;
  &lt;/Content&gt;
&lt;/Document&gt;</slidetranscript>
      <slidetranscript slideid="6YKdHbCITe9.6Kl0sDjiHne" slidebank="false" type="slide" noteswf="" notespng="" pathlib="Lib" pathindex="5">&lt;Document xmlns:xsi="http://www.w3.org/2001/XMLSchema-instance" xmlns:xsd="http://www.w3.org/2001/XMLSchema"&gt;
  &lt;Content&gt;
    &lt;Block&gt;
      &lt;Style LineSpacingRule="SinglePt5" LineSpacing="30" /&gt;
      &lt;Span Text="Introduction&amp;#xA;"&gt;
        &lt;Style FontFamily="Articulate Narrow" /&gt;
      &lt;/Span&gt;
    &lt;/Block&gt;
    &lt;Block&gt;
      &lt;Style LineSpacingRule="SinglePt5" LineSpacing="30" /&gt;
      &lt;Span Text="&amp;#xA;"&gt;
        &lt;Style FontFamily="Articulate Narrow" /&gt;
      &lt;/Span&gt;
    &lt;/Block&gt;
    &lt;Block&gt;
      &lt;Style LineSpacingRule="SinglePt5" LineSpacing="30" /&gt;
      &lt;Span Text="Sleep is an important part of your daily routineyou spend about one-third of your time doing it.  Quality sleep  and getting enough of it at the right times -- is as essential to survival as food and water.  Without sleep you cant form or maintain the pathways in your brain that let you learn and create new memories, and its harder to concentrate and respond quickly."&gt;
        &lt;Style FontFamily="Articulate Narrow" /&gt;
      &lt;/Span&gt;
    &lt;/Block&gt;
  &lt;/Content&gt;
&lt;/Document&gt;</slidetranscript>
      <slidetranscript slideid="6YKdHbCITe9.6DoCSZYwBOX" slidebank="false" type="slide" noteswf="" notespng="" pathlib="Lib" pathindex="6">&lt;Document xmlns:xsi="http://www.w3.org/2001/XMLSchema-instance" xmlns:xsd="http://www.w3.org/2001/XMLSchema"&gt;
  &lt;Content&gt;
    &lt;Block&gt;
      &lt;Style Justification="Left" LineSpacingRule="SinglePt5" LineSpacing="30" /&gt;
      &lt;Span Text="A sleep disorder is any condition that involves difficulty experienced when sleeping. Such disorders often result in daytime fatigue, causing severe distress and impairment to work, and social or personal functioning. Sleep disorders are extremely common in the general population and can lead to significant morbidity. Sleep disorders may cause or exacerbate preexisting medical and psychiatric conditions and are associated with high rates of depression, anxiety, and impaired daytime functioning"&gt;
        &lt;Style FontFamily="Articulate Narrow" /&gt;
      &lt;/Span&gt;
    &lt;/Block&gt;
  &lt;/Content&gt;
&lt;/Document&gt;</slidetranscript>
      <slidetranscript slideid="6YKdHbCITe9.6TZjQaSGbYG" slidebank="false" type="slide" noteswf="" notespng="" pathlib="Lib" pathindex="7">&lt;Document xmlns:xsi="http://www.w3.org/2001/XMLSchema-instance" xmlns:xsd="http://www.w3.org/2001/XMLSchema"&gt;
  &lt;Content&gt;
    &lt;Block&gt;
      &lt;Style /&gt;
      &lt;Span Text="what is sleep?&amp;#xA;" /&gt;
    &lt;/Block&gt;
    &lt;Block&gt;
      &lt;Style /&gt;
      &lt;Span Text="&amp;#xA;" /&gt;
    &lt;/Block&gt;
    &lt;Block&gt;
      &lt;Style /&gt;
      &lt;Span Text="Sleep is a complex biological process. While you are sleeping, you are unconscious, but your brain and body functions are still active. They are doing a number of important jobs that help you stay healthy and function at your best. So when you don't get enough quality sleep, it does more than just make you feel tired. It can affect your physical and mental health, thinking, and daily functioning." /&gt;
    &lt;/Block&gt;
  &lt;/Content&gt;
&lt;/Document&gt;</slidetranscript>
      <slidetranscript slideid="6YKdHbCITe9.6qGcPo3iNYn" slidebank="false" type="slide" noteswf="" notespng="" pathlib="Lib" pathindex="8">&lt;Document xmlns:xsi="http://www.w3.org/2001/XMLSchema-instance" xmlns:xsd="http://www.w3.org/2001/XMLSchema"&gt;
  &lt;Content&gt;
    &lt;Block&gt;
      &lt;Style Justification="Left" /&gt;
      &lt;Span Text="Click on each card to know more about different types of sleep disorders."&gt;
        &lt;Style FontFamily="Century Gothic" FontSize="16" FontIsBold="True" ForegroundColor="#293E55" DisplayCase="AsIs" LinkColor="#293E55" /&gt;
      &lt;/Span&gt;
      &lt;Span Text="&amp;#xA;"&gt;
        &lt;Style FontFamily="Andalus" ForegroundColor="lt1,00" LinkColor="lt1,00" /&gt;
      &lt;/Span&gt;
    &lt;/Block&gt;
    &lt;Block&gt;
      &lt;Style /&gt;
      &lt;Span Text=""&gt;
        &lt;Style FontFamily="Century Gothic" FontSize="16" FontIsBold="True" ForegroundColor="#293E55" DisplayCase="AsIs" LinkColor="#293E55" /&gt;
      &lt;/Span&gt;
    &lt;/Block&gt;
  &lt;/Content&gt;
&lt;/Document&gt;</slidetranscript>
      <slidetranscript slideid="6PNHMTnhP1v.6XNN1TCYMx4" slidebank="false" type="slide" noteswf="" notespng="" pathlib="Lib" pathindex="9">&lt;Document xmlns:xsi="http://www.w3.org/2001/XMLSchema-instance" xmlns:xsd="http://www.w3.org/2001/XMLSchema"&gt;
  &lt;Content&gt;
    &lt;Block&gt;
      &lt;Style Justification="Center" /&gt;
      &lt;Span Text="What your sleeping position says about your mental health?&amp;#xA;"&gt;
        &lt;Style FontFamily="Century Gothic" /&gt;
      &lt;/Span&gt;
    &lt;/Block&gt;
    &lt;Block&gt;
      &lt;Style Justification="Center" /&gt;
      &lt;Span Text="Click on each icon to reveal information"&gt;
        &lt;Style FontFamily="Century Gothic" FontSize="14" ForegroundColor="lt1,00" LinkColor="lt1,00" /&gt;
      &lt;/Span&gt;
    &lt;/Block&gt;
  &lt;/Content&gt;
&lt;/Document&gt;</slidetranscript>
      <slidetranscript slideid="6PNHMTnhP1v.5Zrhhk90sql" slidebank="false" type="slide" noteswf="" notespng="" pathlib="Lib" pathindex="10">&lt;Document xmlns:xsi="http://www.w3.org/2001/XMLSchema-instance" xmlns:xsd="http://www.w3.org/2001/XMLSchema"&gt;
  &lt;Content&gt;
    &lt;Block&gt;
      &lt;Style /&gt;
      &lt;Span Text="Fetal Sleepers: "&gt;
        &lt;Style FontFamily="Andalus" FontIsBold="True" /&gt;
      &lt;/Span&gt;
      &lt;Span Text="Warm &amp;amp; Conscientious&amp;#xA;"&gt;
        &lt;Style FontFamily="Andalus" /&gt;
      &lt;/Span&gt;
    &lt;/Block&gt;
    &lt;Block&gt;
      &lt;Style /&gt;
      &lt;Span Text="&amp;#xA;"&gt;
        &lt;Style FontFamily="Andalus" /&gt;
      &lt;/Span&gt;
    &lt;/Block&gt;
    &lt;Block&gt;
      &lt;Style /&gt;
      &lt;Span Text="Curling up in the fetal position like a newborn baby signals that youre trying to comfort yourself. Traits include a soft interior which is camouflaged by a tough exterior, shy but warm, conscientious, organized and ready to face the day."&gt;
        &lt;Style FontFamily="Andalus" ForegroundColor="dk1,08" LinkColor="dk1,08" /&gt;
      &lt;/Span&gt;
    &lt;/Block&gt;
  &lt;/Content&gt;
&lt;/Document&gt;</slidetranscript>
      <slidetranscript slideid="6PNHMTnhP1v.6rauxN0wa5a" slidebank="false" type="slide" noteswf="" notespng="" pathlib="Lib" pathindex="11">&lt;Document xmlns:xsi="http://www.w3.org/2001/XMLSchema-instance" xmlns:xsd="http://www.w3.org/2001/XMLSchema"&gt;
  &lt;Content&gt;
    &lt;Block&gt;
      &lt;Style /&gt;
      &lt;Span Text="Back Sleepers: "&gt;
        &lt;Style FontFamily="Andalus" FontIsBold="True" /&gt;
      &lt;/Span&gt;
      &lt;Span Text="High Expectations&amp;#xA;"&gt;
        &lt;Style FontFamily="Andalus" /&gt;
      &lt;/Span&gt;
    &lt;/Block&gt;
    &lt;Block&gt;
      &lt;Style /&gt;
      &lt;Span Text="&amp;#xA;"&gt;
        &lt;Style FontFamily="Andalus" /&gt;
      &lt;/Span&gt;
    &lt;/Block&gt;
    &lt;Block&gt;
      &lt;Style /&gt;
      &lt;Span Text="Sleeping on your back with your arms by your sides, also known as soldier position, reveals that you have high expectations of yourself and others, and practice personal responsibility. Back sleepers are also the more likely to snore."&gt;
        &lt;Style FontFamily="Andalus" ForegroundColor="dk1,08" LinkColor="dk1,08" /&gt;
      &lt;/Span&gt;
    &lt;/Block&gt;
  &lt;/Content&gt;
&lt;/Document&gt;</slidetranscript>
      <slidetranscript slideid="6PNHMTnhP1v.6E32P4X64KM" slidebank="false" type="slide" noteswf="" notespng="" pathlib="Lib" pathindex="12">&lt;Document xmlns:xsi="http://www.w3.org/2001/XMLSchema-instance" xmlns:xsd="http://www.w3.org/2001/XMLSchema"&gt;
  &lt;Content&gt;
    &lt;Block&gt;
      &lt;Style /&gt;
      &lt;Span Text="Free Fall Sleepers: "&gt;
        &lt;Style FontFamily="Andalus" FontIsBold="True" /&gt;
      &lt;/Span&gt;
      &lt;Span Text="Brash &amp;amp; Anxious"&gt;
        &lt;Style FontFamily="Andalus" FontIsBold="False" /&gt;
      &lt;/Span&gt;
      &lt;Span Text="&amp;#xA;"&gt;
        &lt;Style FontFamily="Andalus" /&gt;
      &lt;/Span&gt;
    &lt;/Block&gt;
    &lt;Block&gt;
      &lt;Style /&gt;
      &lt;Span Text="&amp;#xA;"&gt;
        &lt;Style FontFamily="Andalus" /&gt;
      &lt;/Span&gt;
    &lt;/Block&gt;
    &lt;Block&gt;
      &lt;Style /&gt;
      &lt;Span Text="Those who sleep on their stomachs with their arms wide are known as "&gt;
        &lt;Style FontFamily="Andalus" ForegroundColor="dk1,08" LinkColor="dk1,08" /&gt;
      &lt;/Span&gt;
      &lt;Span Text="free fallers. You are likely to be  brash and outgoing but also harbor feelings of anxiety due to feeling overwhelmed during your waking hours."&gt;
        &lt;Style FontFamily="Andalus" FontIsBold="False" ForegroundColor="dk1,08" DisplayCase="AsIs" LinkColor="dk1,08" /&gt;
      &lt;/Span&gt;
    &lt;/Block&gt;
  &lt;/Content&gt;
&lt;/Document&gt;</slidetranscript>
      <slidetranscript slideid="6PNHMTnhP1v.6AUyCcUFy6v" slidebank="false" type="slide" noteswf="" notespng="" pathlib="Lib" pathindex="13">&lt;Document xmlns:xsi="http://www.w3.org/2001/XMLSchema-instance" xmlns:xsd="http://www.w3.org/2001/XMLSchema"&gt;
  &lt;Content&gt;
    &lt;Block&gt;
      &lt;Style /&gt;
      &lt;Span Text="Left Side Sleepers: "&gt;
        &lt;Style FontFamily="Andalus" FontIsBold="True" /&gt;
      &lt;/Span&gt;
      &lt;Span Text="Creative and Curious"&gt;
        &lt;Style FontFamily="Andalus" FontIsBold="False" /&gt;
      &lt;/Span&gt;
      &lt;Span Text="&amp;#xA;"&gt;
        &lt;Style FontFamily="Andalus" /&gt;
      &lt;/Span&gt;
    &lt;/Block&gt;
    &lt;Block&gt;
      &lt;Style /&gt;
      &lt;Span Text="&amp;#xA;"&gt;
        &lt;Style FontFamily="Andalus" /&gt;
      &lt;/Span&gt;
    &lt;/Block&gt;
    &lt;Block&gt;
      &lt;Style /&gt;
      &lt;Span Text="People who favor sleeping on their left sides are more likely to work in the literary and performing arts, marketing and advertising, and have a high level of education."&gt;
        &lt;Style FontFamily="Andalus" ForegroundColor="dk1,08" LinkColor="dk1,08" /&gt;
      &lt;/Span&gt;
    &lt;/Block&gt;
  &lt;/Content&gt;
&lt;/Document&gt;</slidetranscript>
      <slidetranscript slideid="6PNHMTnhP1v.6JbCtMPbBpW" slidebank="false" type="slide" noteswf="" notespng="" pathlib="Lib" pathindex="14">&lt;Document xmlns:xsi="http://www.w3.org/2001/XMLSchema-instance" xmlns:xsd="http://www.w3.org/2001/XMLSchema"&gt;
  &lt;Content&gt;
    &lt;Block&gt;
      &lt;Style /&gt;
      &lt;Span Text="Heron sleeper: "&gt;
        &lt;Style FontFamily="Andalus" FontIsBold="True" /&gt;
      &lt;/Span&gt;
      &lt;Span Text="Unpredictable"&gt;
        &lt;Style FontFamily="Andalus" FontIsBold="False" /&gt;
      &lt;/Span&gt;
      &lt;Span Text="&amp;#xA;"&gt;
        &lt;Style FontFamily="Andalus" /&gt;
      &lt;/Span&gt;
    &lt;/Block&gt;
    &lt;Block&gt;
      &lt;Style /&gt;
      &lt;Span Text="&amp;#xA;"&gt;
        &lt;Style FontFamily="Andalus" /&gt;
      &lt;/Span&gt;
    &lt;/Block&gt;
    &lt;Block&gt;
      &lt;Style /&gt;
      &lt;Span Text="If you generally sleep with your arms and legs splayed, you're a heron sleeper. Heron sleepers are moody,  unpredictable, and have a hard time making decisions."&gt;
        &lt;Style FontFamily="Andalus" ForegroundColor="dk1,08" LinkColor="dk1,08" /&gt;
      &lt;/Span&gt;
    &lt;/Block&gt;
  &lt;/Content&gt;
&lt;/Document&gt;</slidetranscript>
      <slidetranscript slideid="6PNHMTnhP1v.6UqXXunOoIg" slidebank="false" type="slide" noteswf="" notespng="" pathlib="Lib" pathindex="15">&lt;Document xmlns:xsi="http://www.w3.org/2001/XMLSchema-instance" xmlns:xsd="http://www.w3.org/2001/XMLSchema"&gt;
  &lt;Content&gt;
    &lt;Block&gt;
      &lt;Style /&gt;
      &lt;Span Text="Starfish sleepers: "&gt;
        &lt;Style FontFamily="Andalus" FontIsBold="True" /&gt;
      &lt;/Span&gt;
      &lt;Span Text="Great Friends"&gt;
        &lt;Style FontFamily="Andalus" FontIsBold="False" /&gt;
      &lt;/Span&gt;
      &lt;Span Text="&amp;#xA;"&gt;
        &lt;Style FontFamily="Andalus" /&gt;
      &lt;/Span&gt;
    &lt;/Block&gt;
    &lt;Block&gt;
      &lt;Style /&gt;
      &lt;Span Text="&amp;#xA;"&gt;
        &lt;Style FontFamily="Andalus" /&gt;
      &lt;/Span&gt;
    &lt;/Block&gt;
    &lt;Block&gt;
      &lt;Style /&gt;
      &lt;Span Text="If you sleep on your back with your arms wide, you're a starfish sleeper. Starfish sleeper prefer not to be center of attention, and their keen listening skills make them trusted friends and confidants."&gt;
        &lt;Style FontFamily="Andalus" ForegroundColor="dk1,08" LinkColor="dk1,08" /&gt;
      &lt;/Span&gt;
    &lt;/Block&gt;
  &lt;/Content&gt;
&lt;/Document&gt;</slidetranscript>
      <slidetranscript slideid="6PNHMTnhP1v.6GagMXraupb" slidebank="false" type="slide" noteswf="" notespng="" pathlib="Lib" pathindex="16">&lt;Document xmlns:xsi="http://www.w3.org/2001/XMLSchema-instance" xmlns:xsd="http://www.w3.org/2001/XMLSchema"&gt;
  &lt;Content&gt;
    &lt;Block&gt;
      &lt;Style /&gt;
      &lt;Span Text="Right side sleepers: "&gt;
        &lt;Style FontFamily="Andalus" FontIsBold="True" /&gt;
      &lt;/Span&gt;
      &lt;Span Text="Risk and rewards"&gt;
        &lt;Style FontFamily="Andalus" FontIsBold="False" /&gt;
      &lt;/Span&gt;
      &lt;Span Text="&amp;#xA;"&gt;
        &lt;Style FontFamily="Andalus" /&gt;
      &lt;/Span&gt;
    &lt;/Block&gt;
    &lt;Block&gt;
      &lt;Style /&gt;
      &lt;Span Text="&amp;#xA;"&gt;
        &lt;Style FontFamily="Andalus" ForegroundColor="dk1,08" LinkColor="dk1,08" /&gt;
      &lt;/Span&gt;
    &lt;/Block&gt;
    &lt;Block&gt;
      &lt;Style /&gt;
      &lt;Span Text="Right side sleepers were more likely to take risk. They are more likely to consume caffeine, gamble and challenge norms. Right side sleepers are attracted to logistics, transportation, and entrepreneurial pursuits."&gt;
        &lt;Style FontFamily="Andalus" ForegroundColor="dk1,08" LinkColor="dk1,08" /&gt;
      &lt;/Span&gt;
    &lt;/Block&gt;
  &lt;/Content&gt;
&lt;/Document&gt;</slidetranscript>
      <slidetranscript slideid="5XomhFIOu5j.6FBk6TsA0h0" slidebank="false" type="slide" noteswf="" notespng="" pathlib="Lib" pathindex="17">&lt;Document xmlns:xsi="http://www.w3.org/2001/XMLSchema-instance" xmlns:xsd="http://www.w3.org/2001/XMLSchema"&gt;
  &lt;Content&gt;
    &lt;Block&gt;
      &lt;Style Justification="Center" LineSpacingRule="Single" LineSpacing="20" /&gt;
      &lt;Span Text="Following are the some of foods that needs to be avoided before you go to bed.&amp;#xA;"&gt;
        &lt;Style FontFamily="Comic Sans MS" FontIsBold="True" ForegroundColor="#F79228" LinkColor="#F79228" /&gt;
      &lt;/Span&gt;
    &lt;/Block&gt;
    &lt;Block&gt;
      &lt;Style Justification="Center" LineSpacingRule="Single" LineSpacing="20" /&gt;
      &lt;Span Text="&amp;#xA;"&gt;
        &lt;Style FontFamily="Comic Sans MS" FontIsBold="True" ForegroundColor="#F79228" LinkColor="#F79228" /&gt;
      &lt;/Span&gt;
    &lt;/Block&gt;
    &lt;Block&gt;
      &lt;Style Justification="Center" LineSpacingRule="Single" LineSpacing="20" /&gt;
      &lt;Span Text="COFFEE&amp;#xA;"&gt;
        &lt;Style FontFamily="Comic Sans MS" FontIsBold="True" ForegroundColor="#F79228" LinkColor="#F79228" /&gt;
      &lt;/Span&gt;
    &lt;/Block&gt;
    &lt;Block&gt;
      &lt;Style Justification="Center" LineSpacingRule="Single" LineSpacing="20" /&gt;
      &lt;Span Text="&amp;#xA;"&gt;
        &lt;Style FontFamily="Comic Sans MS" FontIsBold="True" ForegroundColor="#F79228" LinkColor="#F79228" /&gt;
      &lt;/Span&gt;
    &lt;/Block&gt;
    &lt;Block&gt;
      &lt;Style Justification="Center" LineSpacingRule="Single" LineSpacing="20" /&gt;
      &lt;Span Text="ALCOHOL&amp;#xA;"&gt;
        &lt;Style FontFamily="Comic Sans MS" FontIsBold="True" ForegroundColor="#F79228" LinkColor="#F79228" /&gt;
      &lt;/Span&gt;
    &lt;/Block&gt;
    &lt;Block&gt;
      &lt;Style Justification="Center" LineSpacingRule="Single" LineSpacing="20" /&gt;
      &lt;Span Text="&amp;#xA;"&gt;
        &lt;Style FontFamily="Comic Sans MS" FontIsBold="True" ForegroundColor="#F79228" LinkColor="#F79228" /&gt;
      &lt;/Span&gt;
    &lt;/Block&gt;
    &lt;Block&gt;
      &lt;Style Justification="Center" LineSpacingRule="Single" LineSpacing="20" /&gt;
      &lt;Span Text="CHOCOLATE&amp;#xA;"&gt;
        &lt;Style FontFamily="Comic Sans MS" FontIsBold="True" ForegroundColor="#F79228" LinkColor="#F79228" /&gt;
      &lt;/Span&gt;
    &lt;/Block&gt;
    &lt;Block&gt;
      &lt;Style Justification="Center" LineSpacingRule="Single" LineSpacing="20" /&gt;
      &lt;Span Text="&amp;#xA;"&gt;
        &lt;Style FontFamily="Comic Sans MS" FontIsBold="True" ForegroundColor="#F79228" LinkColor="#F79228" /&gt;
      &lt;/Span&gt;
    &lt;/Block&gt;
    &lt;Block&gt;
      &lt;Style Justification="Center" LineSpacingRule="Single" LineSpacing="20" /&gt;
      &lt;Span Text="HEAY FOOD"&gt;
        &lt;Style FontFamily="Comic Sans MS" FontIsBold="True" ForegroundColor="#F79228" LinkColor="#F79228" /&gt;
      &lt;/Span&gt;
    &lt;/Block&gt;
  &lt;/Content&gt;
&lt;/Document&gt;</slidetranscript>
      <slidetranscript slideid="6WodivaGol5.6hUTERS2Wo4" slidebank="false" type="slide" noteswf="" notespng="" pathlib="Lib" pathindex="18">&lt;Document xmlns:xsi="http://www.w3.org/2001/XMLSchema-instance" xmlns:xsd="http://www.w3.org/2001/XMLSchema"&gt;
  &lt;Content&gt;
    &lt;Block&gt;
      &lt;Style Justification="Center" /&gt;
      &lt;Span Text="Match the following: Drag the numbers &amp;amp; drop it near to the appropriate sleep position &amp;#xA;"&gt;
        &lt;Style FontFamily="Century Gothic" FontIsBold="True" /&gt;
      &lt;/Span&gt;
    &lt;/Block&gt;
    &lt;Block&gt;
      &lt;Style Justification="Center" /&gt;
      &lt;Span Text="then click on submit button below."&gt;
        &lt;Style FontFamily="Century Gothic" FontIsBold="True" /&gt;
      &lt;/Span&gt;
    &lt;/Block&gt;
  &lt;/Content&gt;
&lt;/Document&gt;</slidetranscript>
    </slidetranscripts>
  </transcript_data>
  <glossary_data />
</bwFrame>